crdt.py
crdt-0.0.1.dist-info/entry_points.txt
crdt-0.0.1.dist-info/WHEEL
crdt-0.0.1.dist-info/METADATA
crdt-0.0.1.dist-info/RECORD
